pypanda/__init__.py
pypanda/alicloud/__init__.py
pypanda/alicloud/_manager.py
pypanda/alicloud/amqp_manager.py
pypanda/alicloud/billing_manager.py
pypanda/alicloud/credential_helper.py
pypanda/alicloud/decorator.py
pypanda/alicloud/dns_manager.py
pypanda/alicloud/ecs_manager.py
pypanda/alicloud/exceptions.py
pypanda/alicloud/k8s_manager.py
pypanda/alicloud/kv_manager.py
pypanda/alicloud/mongo_manger.py
pypanda/alicloud/oss_manager.py
pypanda/alicloud/ram_manager.py
pypanda/alicloud/rds_manager.py
pypanda/alicloud/resource_manager.py
pypanda/alicloud/slb_manager.py
pypanda/alicloud/sts_manager.py
pypanda/alicloud/vpc_manager.py
pypanda_alicloud-1.0.0.dist-info/WHEEL
pypanda_alicloud-1.0.0.dist-info/METADATA
pypanda_alicloud-1.0.0.dist-info/RECORD
