Metadata-Version: 2.1
Name: pypanda-alicloud
Version: 1.0.0
Summary: python libs for alicloud
Author: zhuqian
Author-email: zhuqian@justcalm.ink
Requires-Python: >=3.10,<4.0
Classifier: Programming Language :: Python :: 3
Classifier: Programming Language :: Python :: 3.10
Classifier: Programming Language :: Python :: 3.11
Requires-Dist: alibabacloud-alidns20150109 (>=3.0.0,<4.0.0)
Requires-Dist: alibabacloud-amqp-open20191212 (>=1.0.1,<2.0.0)
Requires-Dist: alibabacloud-bssopenapi20171214 (==2.0.6)
Requires-Dist: alibabacloud-cs20151215 (>=3.0.19,<4.0.0)
Requires-Dist: alibabacloud-dds20151201 (>=3.6.11,<4.0.0)
Requires-Dist: alibabacloud-ecs20140526 (>=3.0.1,<4.0.0)
Requires-Dist: alibabacloud-oss20190517 (>=1.0.5,<2.0.0)
Requires-Dist: alibabacloud-r-kvstore20150101 (>=2.20.5,<3.0.0)
Requires-Dist: alibabacloud-ram20150501 (>=1.0.3,<2.0.0)
Requires-Dist: alibabacloud-rds20140815 (>=2.1.1,<3.0.0)
Requires-Dist: alibabacloud-resourcemanager20200331 (==2.1.1)
Requires-Dist: alibabacloud-slb20140515 (>=3.3.17,<4.0.0)
Requires-Dist: alibabacloud-sts20150401 (==1.1.2)
Requires-Dist: alibabacloud-vpc20160428 (==2.0.10)
Requires-Dist: install (>=1.3.5,<2.0.0)
Requires-Dist: pip (>=22.3,<23.0)
